{"Traces":[{"CenterLatitude":32.895879,"CenterLongitude":115.821389,"ZoomLevel":8,"Lines":[{"Markers":[{"Id":"863776960dec44f8822d80e08049261d","Latitude":32.895879,"Longitude":115.821389,"OffsetLeft":0,"OffsetTop":0,"Invisible":true,"RegionId":"CN3412","Title":"阜阳"},{"Id":"4ab5eef8c4344ecb96d7d49066a3de3e","Latitude":29.711328,"Longitude":116.007993,"OffsetLeft":0,"OffsetTop":0,"Invisible":true,"RegionId":"CN3604","Title":"九江"},{"Id":"0def64725d684b4c9b9f8c971106fabe","Latitude":32.195688,"Longitude":119.431494,"OffsetLeft":0,"OffsetTop":0,"Invisible":true,"RegionId":"CN3211","Title":"镇江"},{"Id":"b35cff77e1bc4f2c8ae8ce55fbe9469b","Latitude":29.711328,"Longitude":116.007993,"OffsetLeft":0,"OffsetTop":0,"Invisible":true,"RegionId":"CN3604","Title":"九江"},{"Id":"2e7b082b174740649f7dab31093a431b","Latitude":32.895879,"Longitude":115.821389,"OffsetLeft":0,"OffsetTop":0,"Invisible":true,"RegionId":"CN3412","Title":"阜阳"},{"Id":"e83b788f7eb446bb9ef983d52366507b","Latitude":34.802941,"Longitude":114.313904,"OffsetLeft":0,"OffsetTop":0,"Invisible":true,"RegionId":"CN4102","Title":"开封"},{"Id":"b10c8805323d4e27b6cd8330849b56c5","Latitude":32.895879,"Longitude":115.821389,"OffsetLeft":0,"OffsetTop":0,"Invisible":true,"RegionId":"CN3412","Title":"阜阳"},{"Id":"a8310ed1a71c4ef09c5b553bfaea7b86","Latitude":31.575549,"Longitude":118.504404,"OffsetLeft":0,"OffsetTop":0,"Invisible":true,"RegionId":"CN340521","Title":"当涂"},{"Id":"428af08113c14b8499dde6ee58846aa5","Latitude":32.895879,"Longitude":115.821389,"OffsetLeft":0,"OffsetTop":0,"Invisible":true,"RegionId":"CN3412","Title":"阜阳"},{"Id":"37419f885ee545f48c8ff0b51a7a55ab","Latitude":34.420378,"Longitude":115.662798,"OffsetLeft":0,"OffsetTop":0,"Invisible":true,"RegionId":"CN4114","Title":"商丘"},{"Id":"fde3067b29644f0b9dbcc291b11dc67f","Latitude":34.802941,"Longitude":114.313904,"OffsetLeft":0,"OffsetTop":0,"Invisible":true,"RegionId":"CN4102","Title":"开封"},{"Id":"1b43d7a4ae984b91b590f844cc398104","Latitude":32.996701,"Longitude":112.535009,"OffsetLeft":0,"OffsetTop":0,"Invisible":true,"RegionId":"CN4113","Title":"南阳"},{"Id":"1e21b5008f4e4b14940c7c90602fa420","Latitude":32.895879,"Longitude":115.821389,"OffsetLeft":0,"OffsetTop":0,"Invisible":true,"RegionId":"CN3412","Title":"阜阳"},{"Id":"6af7aef07ee046ee909106b8f43b517b","Latitude":32.39986,"Longitude":119.419107,"OffsetLeft":0,"OffsetTop":0,"Invisible":true,"RegionId":"CN321","Title":"扬州"},{"Id":"14dcd5ec5fbd4fd0930575f493a5efc4","Latitude":32.4612,"Longitude":119.932115,"OffsetLeft":0,"OffsetTop":0,"Invisible":true,"RegionId":"CN3212","Title":"泰州"},{"Id":"0332dd8893f3458aabc922b427e08f6e","Latitude":30.280059,"Longitude":120.161693,"OffsetLeft":0,"OffsetTop":0,"Invisible":true,"RegionId":"CN3301","Title":"杭州"},{"Id":"5e784b9ac5e44cb98853edcc419e999d","Latitude":31.014847,"Longitude":120.639402,"OffsetLeft":0,"OffsetTop":0,"Invisible":true,"RegionId":"CN320509","Title":"吴江"},{"Id":"dce4fcad9900447fa917c2526b3b0323","Latitude":30.280059,"Longitude":120.161693,"OffsetLeft":0,"OffsetTop":0,"Invisible":true,"RegionId":"CN3301","Title":"杭州"},{"Id":"a0d62c57abe74d938fb3e046a6f62918","Latitude":29.594696,"Longitude":120.828141,"OffsetLeft":0,"OffsetTop":0,"Invisible":true,"RegionId":"CN330683","Title":"嵊州"}]}],"Markers":[{"Latitude":32.895879,"Longitude":115.821389,"OffsetLeft":0,"OffsetTop":0,"Invisible":false,"RegionId":"CN3412","Title":"阜阳 (出生地)","Detail":"<div class='label1'><a href='javascript: DetailSwitch(\"863776960dec44f8822d80e08049261d\");'><span id='863776960dec44f8822d80e08049261d_link' class='switch'>—</span></a><a href=\"javascript: ViewDetail('scope=&author=&beginYear=1092&endYear=1106')\">1092-1106年</a>，0-14岁</div><div id='863776960dec44f8822d80e08049261d' class='detail'><a href=\"javascript: ViewDetail('scope=&author=&beginYear=1092&endYear=1092')\">1092年</a>，疑本年生于家乡颍州汝阴，本表所标年岁均为虚拟数，非实数。<br /><a href=\"javascript: ViewDetail('scope=&author=&beginYear=1093&endYear=1106')\">1093-1106年</a>，疑在家乡汝阴家居。<br /></div><div class='label1'><a href='javascript: DetailSwitch(\"2e7b082b174740649f7dab31093a431b\");'><span id='2e7b082b174740649f7dab31093a431b_link' class='switch'>—</span></a><a href=\"javascript: ViewDetail('scope=&author=&beginYear=1110&endYear=1110')\">1110年</a>，18岁</div><div id='2e7b082b174740649f7dab31093a431b' class='detail'><a href=\"javascript: ViewDetail('scope=&author=&beginYear=1110&endYear=1110')\">1110年</a>，与颍上知县洪炎游，著《侍女小名录》<br /></div><div class='label1'><a href='javascript: DetailSwitch(\"b10c8805323d4e27b6cd8330849b56c5\");'><span id='b10c8805323d4e27b6cd8330849b56c5_link' class='switch'>—</span></a><a href=\"javascript: ViewDetail('scope=&author=&beginYear=1114&endYear=1114')\">1114年</a>，22岁</div><div id='b10c8805323d4e27b6cd8330849b56c5' class='detail'><a href=\"javascript: ViewDetail('scope=&author=&beginYear=1114&endYear=1114')\">1114年</a>，在故乡汝阴家居。<br /></div><div class='label1'><a href='javascript: DetailSwitch(\"428af08113c14b8499dde6ee58846aa5\");'><span id='428af08113c14b8499dde6ee58846aa5_link' class='switch'>—</span></a><a href=\"javascript: ViewDetail('scope=&author=&beginYear=1115&endYear=1123')\">1115-1123年</a>，23-31岁</div><div id='428af08113c14b8499dde6ee58846aa5' class='detail'><a href=\"javascript: ViewDetail('scope=&author=&beginYear=1115&endYear=1119')\">1115-1119年</a>，疑在故乡汝阴家居。<br /><a href=\"javascript: ViewDetail('scope=&author=&beginYear=1120&endYear=1120')\">1120年</a>，在故乡汝阴家居，与知府周邦彦相知。<br /><a href=\"javascript: ViewDetail('scope=&author=&beginYear=1121&endYear=1121')\">1121年</a>，在故乡汝阴家居，收到周邦彦所寄《瑞鹤仙》词。<br /><a href=\"javascript: ViewDetail('scope=&author=&beginYear=1122&endYear=1122')\">1122年7月</a>，疑在故乡汝阴家居。七月，著《四六话》成，自为序。<span class='label'>作品：</span>四六话。<span class='inlineComment2'>（《四六话》为二卷。）</span><br /><a href=\"javascript: ViewDetail('scope=&author=&beginYear=1123&endYear=1123')\">1123年</a>，疑在故乡汝阴家居。<br /></div><div class='label1'><a href='javascript: DetailSwitch(\"1e21b5008f4e4b14940c7c90602fa420\");'><span id='1e21b5008f4e4b14940c7c90602fa420_link' class='switch'>—</span></a><a href=\"javascript: ViewDetail('scope=&author=&beginYear=1126&endYear=1126')\">1126年</a>，34岁</div><div id='1e21b5008f4e4b14940c7c90602fa420' class='detail'><a href=\"javascript: ViewDetail('scope=&author=&beginYear=1126&endYear=1126')\">1126年</a>，回到家乡颍州，与郭寿翁相见，遇金人之骑兵占领颍州。<br /></div>"},{"Latitude":29.711328,"Longitude":116.007993,"OffsetLeft":0,"OffsetTop":0,"Invisible":false,"RegionId":"CN3604","Title":"九江","Detail":"<div class='label1'><a href='javascript: DetailSwitch(\"4ab5eef8c4344ecb96d7d49066a3de3e\");'><span id='4ab5eef8c4344ecb96d7d49066a3de3e_link' class='switch'>—</span></a><a href=\"javascript: ViewDetail('scope=&author=&beginYear=1107&endYear=1107')\">1107年</a>，15岁</div><div id='4ab5eef8c4344ecb96d7d49066a3de3e' class='detail'><a href=\"javascript: ViewDetail('scope=&author=&beginYear=1107&endYear=1107')\">1107年</a>，其父王莘知江州，同往。<br /></div><div class='label1'><a href='javascript: DetailSwitch(\"b35cff77e1bc4f2c8ae8ce55fbe9469b\");'><span id='b35cff77e1bc4f2c8ae8ce55fbe9469b_link' class='switch'>—</span></a><a href=\"javascript: ViewDetail('scope=&author=&beginYear=1107&endYear=1110')\">1107-1110年</a>，15-18岁</div><div id='b35cff77e1bc4f2c8ae8ce55fbe9469b' class='detail'><a href=\"javascript: ViewDetail('scope=&author=&beginYear=1107&endYear=1107')\">1107年</a>，秋，于庐山僧祖可、善权以及李彭等结诗社。<br /><a href=\"javascript: ViewDetail('scope=&author=&beginYear=1108&endYear=1110')\">1108-1110年</a>，与父王莘生活在江州。<br /></div>"},{"Latitude":32.195688,"Longitude":119.431494,"OffsetLeft":0,"OffsetTop":0,"Invisible":false,"RegionId":"CN3211","Title":"镇江","Detail":"<div class='label1'><a href='javascript: DetailSwitch(\"0def64725d684b4c9b9f8c971106fabe\");'><span id='0def64725d684b4c9b9f8c971106fabe_link' class='switch'>—</span></a><a href=\"javascript: ViewDetail('scope=&author=&beginYear=1107&endYear=1107')\">1107年</a>，15岁</div><div id='0def64725d684b4c9b9f8c971106fabe' class='detail'><a href=\"javascript: ViewDetail('scope=&author=&beginYear=1107&endYear=1107')\">1107年</a>，受父命，从九江前往京口拜访曾布。<br /></div>"},{"Latitude":34.802941,"Longitude":114.313904,"OffsetLeft":0,"OffsetTop":0,"Invisible":false,"RegionId":"CN4102","Title":"开封","Detail":"<div class='label1'><a href='javascript: DetailSwitch(\"e83b788f7eb446bb9ef983d52366507b\");'><span id='e83b788f7eb446bb9ef983d52366507b_link' class='switch'>—</span></a><a href=\"javascript: ViewDetail('scope=&author=&beginYear=1111&endYear=1113')\">1111-1113年</a>，19-21岁</div><div id='e83b788f7eb446bb9ef983d52366507b' class='detail'><a href=\"javascript: ViewDetail('scope=&author=&beginYear=1111&endYear=1111')\">1111年</a>，与张元干、娄寅亮相识于太学。<br /><a href=\"javascript: ViewDetail('scope=&author=&beginYear=1112&endYear=1112')\">1112年</a>，在太学读书。<br /><a href=\"javascript: ViewDetail('scope=&author=&beginYear=1113&endYear=1113')\">1113年</a>，在太学读书，与表兄高荷相见，有诗。<span class='label'>作品：</span>次韵国香诗。<div class=\"poem\">\r\n<div class=\"title\">次韵国香诗（宋·王铚）</div><div class=\"content\"><p><!--S-->百花零落悲春晚，不复林园门可款。<!--E--></p><p><!--S-->待花结实春已归，到头只有东家<span class=\"small\">①</span>管。<!--E--></p><p><!--S-->楚宫女子春华敷，为云为雨<span class=\"small\">②</span>皆有馀。<!--E--></p><p><!--S-->亲逢一顾倾国色，不解迎人<span class=\"small\">（小集本作入）</span>专城居。<!--E--></p><p><!--S-->目成未到投梭处，后会<span class=\"small\">③</span>难凭人已去。<!--E--></p><p><!--S-->可怜天壤擅诗声，不如崔护桃花句。<!--E--></p><p><!--S-->坐令永抱埋玉悲，游手<span class=\"small\">（小集本作子）</span>那知京兆眉。<!--E--></p><p><!--S-->难堪别<span class=\"small\">④</span>鹤分飞后，犹是惊鸿初见时。<!--E--></p><p><!--S-->新欢密爱应长久，暂向华筵赏宾友。<!--E--></p><p><!--S-->舞尽春风力不禁，困里腰肢一涡<span class=\"small\">（小集本作树）</span>柳。<!--E--></p><p><!--S-->座上何人赠翠翘，蜀中<span class=\"small\">（小集本作州）</span>风调尤情饶。<!--E--></p><p><!--S-->欢浓酒晕上玉颊，香暖红酥疑欲销。<!--E--></p><p><!--S-->佳人薄命古相似，先后乃逢天下士。<!--E--></p><p><!--S-->但惜盈盈一水时，当年不寄相思字。<!--E--></p><p><!--S-->宜州遗恨君能详，瘴云万里空悲凉。<!--E--></p><p><!--S-->无限风流等閒别，几人赏鉴<span class=\"small\">⑤</span>得黄香。<!--E--></p></div><!--CE--><div class=\"footer\"><span class=\"label\">按：</span><span class=\"comment\">① 小集本、李本作风　② 小集本作为雨为云　③ 小集本作会后　④ 原作白，据小集本改　⑤ 小集本作鉴赏</span></div></div>\r\n<br /></div><div class='label1'><a href='javascript: DetailSwitch(\"fde3067b29644f0b9dbcc291b11dc67f\");'><span id='fde3067b29644f0b9dbcc291b11dc67f_link' class='switch'>—</span></a><a href=\"javascript: ViewDetail('scope=&author=&beginYear=1125&endYear=1125')\">1125年</a>，33岁</div><div id='fde3067b29644f0b9dbcc291b11dc67f' class='detail'><a href=\"javascript: ViewDetail('scope=&author=&beginYear=1125&endYear=1125')\">1125年2月</a>，居京城。二月，为张元干所辑先祖手泽作跋。<span class='label'>作品：</span>跋张元干辑先祖手泽。<br /><a href=\"javascript: ViewDetail('scope=&author=&beginYear=1125&endYear=1125')\">1125年</a>，春，与江端友至相蓝算命。<br /><a href=\"javascript: ViewDetail('scope=&author=&beginYear=1125&endYear=1125')\">1125年</a>，与王伦交往，离开京城。<br /></div>"},{"Latitude":31.575549,"Longitude":118.504404,"OffsetLeft":0,"OffsetTop":0,"Invisible":false,"RegionId":"CN340521","Title":"当涂","Detail":"<div class='label1'><a href='javascript: DetailSwitch(\"a8310ed1a71c4ef09c5b553bfaea7b86\");'><span id='a8310ed1a71c4ef09c5b553bfaea7b86_link' class='switch'>—</span></a><a href=\"javascript: ViewDetail('scope=&author=&beginYear=1114&endYear=1114')\">1114年</a>，22岁</div><div id='a8310ed1a71c4ef09c5b553bfaea7b86' class='detail'><a href=\"javascript: ViewDetail('scope=&author=&beginYear=1114&endYear=1114')\">1114年</a>，从汝阴前往宣城，途径当涂，以《欧阳修别集》示李之仪。<br /></div>"},{"Latitude":34.420378,"Longitude":115.662798,"OffsetLeft":0,"OffsetTop":0,"Invisible":false,"RegionId":"CN4114","Title":"商丘","Detail":"<div class='label1'><a href='javascript: DetailSwitch(\"37419f885ee545f48c8ff0b51a7a55ab\");'><span id='37419f885ee545f48c8ff0b51a7a55ab_link' class='switch'>—</span></a><a href=\"javascript: ViewDetail('scope=&author=&beginYear=1124&endYear=1124')\">1124年</a>，32岁</div><div id='37419f885ee545f48c8ff0b51a7a55ab' class='detail'><a href=\"javascript: ViewDetail('scope=&author=&beginYear=1124&endYear=1124')\">1124年</a>，秋，在睢阳结识晁说之。<br /></div>"},{"Latitude":32.996701,"Longitude":112.535009,"OffsetLeft":0,"OffsetTop":0,"Invisible":false,"RegionId":"CN4113","Title":"南阳","Detail":"<div class='label1'><a href='javascript: DetailSwitch(\"1b43d7a4ae984b91b590f844cc398104\");'><span id='1b43d7a4ae984b91b590f844cc398104_link' class='switch'>—</span></a><a href=\"javascript: ViewDetail('scope=&author=&beginYear=1126&endYear=1126')\">1126年</a>，34岁</div><div id='1b43d7a4ae984b91b590f844cc398104' class='detail'><a href=\"javascript: ViewDetail('scope=&author=&beginYear=1126&endYear=1126')\">1126年</a>，入西道总管王襄幕府，为草檄文。<span class='label'>作品：</span>靖康讨虏檄文。<br /></div>"},{"Latitude":32.39986,"Longitude":119.419107,"OffsetLeft":0,"OffsetTop":0,"Invisible":false,"RegionId":"CN321","Title":"扬州","Detail":"<div class='label1'><a href='javascript: DetailSwitch(\"6af7aef07ee046ee909106b8f43b517b\");'><span id='6af7aef07ee046ee909106b8f43b517b_link' class='switch'>—</span></a><a href=\"javascript: ViewDetail('scope=&author=&beginYear=1127&endYear=1127')\">1127年</a>，35岁</div><div id='6af7aef07ee046ee909106b8f43b517b' class='detail'><a href=\"javascript: ViewDetail('scope=&author=&beginYear=1127&endYear=1127')\">1127年</a>，举家迁至扬州。秋，曾往真州访晁说之。<br /></div>"},{"Latitude":32.4612,"Longitude":119.932115,"OffsetLeft":0,"OffsetTop":0,"Invisible":false,"RegionId":"CN3212","Title":"泰州","Detail":"<div class='label1'><a href='javascript: DetailSwitch(\"14dcd5ec5fbd4fd0930575f493a5efc4\");'><span id='14dcd5ec5fbd4fd0930575f493a5efc4_link' class='switch'>—</span></a><a href=\"javascript: ViewDetail('scope=&author=&beginYear=1128&endYear=1128')\">1128年</a>，36岁</div><div id='14dcd5ec5fbd4fd0930575f493a5efc4' class='detail'><a href=\"javascript: ViewDetail('scope=&author=&beginYear=1128&endYear=1128')\">1128年</a>，南迁途中，在海陵拜访晁说之。<br /></div>"},{"Latitude":30.280059,"Longitude":120.161693,"OffsetLeft":0,"OffsetTop":0,"Invisible":false,"RegionId":"CN3301","Title":"杭州","Detail":"<div class='label1'><a href='javascript: DetailSwitch(\"0332dd8893f3458aabc922b427e08f6e\");'><span id='0332dd8893f3458aabc922b427e08f6e_link' class='switch'>—</span></a><a href=\"javascript: ViewDetail('scope=&author=&beginYear=1129&endYear=1131')\">1129-1131年</a>，37-39岁</div><div id='0332dd8893f3458aabc922b427e08f6e' class='detail'><a href=\"javascript: ViewDetail('scope=&author=&beginYear=1129&endYear=1129')\">1129年</a>，入浙西康允之幕府，有文。<span class='label'>作品：</span>与浙西帅康允之书。<span class='inlineComment2'>（建炎三年升杭州为临安府。）</span><br /><a href=\"javascript: ViewDetail('scope=&author=&beginYear=1129&endYear=1129')\">1129年11月</a>，十一月，跋范宗尹丞相家藏《兰亭贴》<span class='label'>作品：</span>跋范丞相家藏兰亭贴。<br /><a href=\"javascript: ViewDetail('scope=&author=&beginYear=1130&endYear=1130')\">1130年7月</a>，七月，始著《祖宗兵制》<br /><a href=\"javascript: ViewDetail('scope=&author=&beginYear=1130&endYear=1130')\">1130年10月</a>，十月，楚州镇抚使守城战死，高宗命王铚著《赵立传》<br /><a href=\"javascript: ViewDetail('scope=&author=&beginYear=1130&endYear=1130')\">1130年</a>，作《嵊县修学碑》<br /><a href=\"javascript: ViewDetail('scope=&author=&beginYear=1131&endYear=1131')\">1131年11月</a>，得娄寅亮赠《上高宗皇帝书》<br /></div><div class='label1'><a href='javascript: DetailSwitch(\"dce4fcad9900447fa917c2526b3b0323\");'><span id='dce4fcad9900447fa917c2526b3b0323_link' class='switch'>—</span></a><a href=\"javascript: ViewDetail('scope=&author=&beginYear=1133&endYear=1136')\">1133-1136年</a>，41-44岁</div><div id='dce4fcad9900447fa917c2526b3b0323' class='detail'><a href=\"javascript: ViewDetail('scope=&author=&beginYear=1133&endYear=1133')\">1133年</a>，在临安为官。<br /><a href=\"javascript: ViewDetail('scope=&author=&beginYear=1134&endYear=1134')\">1134年3月</a>，三月，朝廷欲用为太府寺丞，被言者谏止。<br /><a href=\"javascript: ViewDetail('scope=&author=&beginYear=1135&endYear=1135')\">1135年</a>，主管庐山太平观，作隐居浙东之计。有诗。<span class='label'>作品：</span>送郭寿翁还庐陵。<div class=\"poem\">\r\n<div class=\"title\">送郭寿翁还庐陵（宋·王铚）<br />　　七言律诗　押庚韵</div><div class=\"content\"><p><!--S-->共遭胡<span class=\"small\">①</span>骑汝阴城，十载相逢尚甲兵。<!--E--></p><p><!--S-->万里鹓鸿自鶱举，九关虎豹任纵横。<!--E--></p><p><!--S-->雨昏山远行人恨，日暮草长幽鸟声。<!--E--></p><p><!--S-->只有别离心似旧，乱来难得是交情。<!--E--></p></div><!--CE--><div class=\"footer\"><span class=\"label\">按：</span><span class=\"comment\">① 原作敌，据初本改</span></div></div>\r\n<br /><a href=\"javascript: ViewDetail('scope=&author=&beginYear=1136&endYear=1136')\">1136年</a>，朱敦儒、徐度来访，命次子王明清出拜二公。<br /></div>"},{"Latitude":31.014847,"Longitude":120.639402,"OffsetLeft":0,"OffsetTop":0,"Invisible":false,"RegionId":"CN320509","Title":"吴江","Detail":"<div class='label1'><a href='javascript: DetailSwitch(\"5e784b9ac5e44cb98853edcc419e999d\");'><span id='5e784b9ac5e44cb98853edcc419e999d_link' class='switch'>—</span></a><a href=\"javascript: ViewDetail('scope=&author=&beginYear=1132&endYear=1132')\">1132年</a>，40岁</div><div id='5e784b9ac5e44cb98853edcc419e999d' class='detail'><a href=\"javascript: ViewDetail('scope=&author=&beginYear=1132&endYear=1132')\">1132年1月</a>，正月，游平江包山禅寺，有文。<span class='label'>作品：</span>包山禅院记。<span class='inlineComment2'>（政和三年升苏州为平江府。）</span><br /></div>"},{"Latitude":29.594696,"Longitude":120.828141,"OffsetLeft":0,"OffsetTop":0,"Invisible":false,"RegionId":"CN330683","Title":"嵊州","Detail":"<div class='label1'><a href='javascript: DetailSwitch(\"a0d62c57abe74d938fb3e046a6f62918\");'><span id='a0d62c57abe74d938fb3e046a6f62918_link' class='switch'>—</span></a><a href=\"javascript: ViewDetail('scope=&author=&beginYear=1137&endYear=1144')\">1137-1144年</a>，45-52岁</div><div id='a0d62c57abe74d938fb3e046a6f62918' class='detail'><a href=\"javascript: ViewDetail('scope=&author=&beginYear=1137&endYear=1137')\">1137年</a>，避居剡溪，有文。<span class='label'>作品：</span>游东山记。<span class='inlineComment2'>（绍兴元年升越州为绍兴府。）</span><br /><a href=\"javascript: ViewDetail('scope=&author=&beginYear=1138&endYear=1138')\">1138年</a>，因修《国朝史述》，被诏奉祠，主管台州崇道观。<br /><a href=\"javascript: ViewDetail('scope=&author=&beginYear=1139&endYear=1139')\">1139年1月</a>，正月，因上《七朝国史》，特迁一官。<br /><a href=\"javascript: ViewDetail('scope=&author=&beginYear=1139&endYear=1139')\">1139年2月</a>，二月，言秦桧所拟徽宗陵名“永固”为后周皇后陵名。<br /><a href=\"javascript: ViewDetail('scope=&author=&beginYear=1140&endYear=1140')\">1140年</a>，闲居山阴。<br /><a href=\"javascript: ViewDetail('scope=&author=&beginYear=1141&endYear=1141')\">1141年</a>，曾为陆游讲王安石欲与司马光卜邻事。<br /><a href=\"javascript: ViewDetail('scope=&author=&beginYear=1142&endYear=1142')\">1142年2月</a>，二月，跋谢文靖《东山图》<br /><a href=\"javascript: ViewDetail('scope=&author=&beginYear=1142&endYear=1142')\">1142年6月</a>，六月，为浙东所刻《两汉记》作后序。<br /><a href=\"javascript: ViewDetail('scope=&author=&beginYear=1143&endYear=1143')\">1143年8月</a>，七八月间，因献《太玄经讲义》，被赐白金三百两。<br /><a href=\"javascript: ViewDetail('scope=&author=&beginYear=1143&endYear=1143')\">1143年</a>，冬，作《题五老图》<br /><a href=\"javascript: ViewDetail('scope=&author=&beginYear=1144&endYear=1144')\">1144年3月</a>，三月，因献《祖宗八朝圣学通纪论》，诏迁一官。<br /><a href=\"javascript: ViewDetail('scope=&author=&beginYear=1144&endYear=1144')\">1144年</a>，春，为判绍兴府孟忠厚筹作不伤时忌对札。<br /><a href=\"javascript: ViewDetail('scope=&author=&beginYear=1144&endYear=1144')\">1144年</a>，夏，卒于绍兴家中。<br /></div>"},{"Latitude":29.560618,"Longitude":115.989402,"OffsetLeft":0,"OffsetTop":0,"Invisible":false,"RegionId":"CN3604 庐山","Title":"庐山"},{"Latitude":31.659391,"Longitude":118.468363,"OffsetLeft":0,"OffsetTop":0,"Invisible":false,"RegionId":"CN3405 采石矶","Title":"采石矶"},{"Latitude":29.605607,"Longitude":120.842762,"OffsetLeft":0,"OffsetTop":0,"Invisible":false,"RegionId":"CN3306 剡溪","Title":"剡溪"}],"Title":"王铚 <span class='inlineComment2'>(1092-1144)</span>","Detail":"<p class='inlineComment2'>引用书目：张明华、房厚信《王铚王明清家族研究》　录入整理：张明华</p><p><a href=\"javascript: ViewRoute(0, 5, 117.6264415, 31.3036035, 9)\">0-18岁</a><br /><a href=\"javascript: ViewPoint(0)\">阜阳</a> → <a href=\"javascript: ViewPoint(1)\">九江</a> → <a href=\"javascript: ViewPoint(2)\">镇江</a> → <a href=\"javascript: ViewPoint(3)\">九江</a> → <a href=\"javascript: ViewPoint(4)\">阜阳</a></p><p><a href=\"javascript: ViewRoute(5, 11, 116.409154, 33.189245, 9)\">19-33岁</a><br /><a href=\"javascript: ViewPoint(5)\">开封</a> → <a href=\"javascript: ViewPoint(6)\">阜阳</a> → <a href=\"javascript: ViewPoint(7)\">当涂</a> → <a href=\"javascript: ViewPoint(8)\">阜阳</a> → <a href=\"javascript: ViewPoint(9)\">商丘</a> → <a href=\"javascript: ViewPoint(10)\">开封</a></p><p><a href=\"javascript: ViewRoute(11, 16, 116.348351, 31.63838, 8)\">34-39岁</a><br /><a href=\"javascript: ViewPoint(11)\">南阳</a> → <a href=\"javascript: ViewPoint(12)\">阜阳</a> → <a href=\"javascript: ViewPoint(13)\">扬州</a> → <a href=\"javascript: ViewPoint(14)\">泰州</a> → <a href=\"javascript: ViewPoint(15)\">杭州</a></p><p><a href=\"javascript: ViewRoute(16, 19, 120.494917, 30.3047715, 10)\">40-52岁</a><br /><a href=\"javascript: ViewPoint(16)\">吴江</a> → <a href=\"javascript: ViewPoint(17)\">杭州</a> → <a href=\"javascript: ViewPoint(18)\">嵊州</a></p>"}]}